{
    "taskName"          : "Задание 7",
    "taskDefinition"    : "Какие три про­мыш­лен­ных объ­ек­та были по­стро­е­ны в годы пер­вых пя­ти­ле­ток? Cоот­вет­ству­ю­щие цифры и за­пи­ши­те в ответ.",
    "mainText"          : "\n1) Дне­прог­эс\n2) Харь­ков­ский трак­тор­ный завод\n3) Волж­ский ав­то­мо­биль­ный завод\n4) Пу­ти­лов­ский завод\n5) Маг­ни­то­гор­ский ме­тал­лур­ги­че­ский ком­би­нат\n6) Транс­си­бир­ская же­лез­ная ма­ги­страль",
    "noValidAnswerTotheRecord"  : false,
    "pictureForNoValidAnswer"   : "",
    "primaryScore"              : 1,
    "onlyOneCorrectAnswer"      : false,
    "divideTheAnswerForEachCharacter": true,
    "mandatorySequence" : false,
    "expectedAnswer"    : "Напр: 13",
    "answers": [
        "1",
        "2",
        "5"
    ],
    "addPictureInTop"           : false,
    "chooseAnswerFromPicker"    : false,
    "arrayExpectedAnswerForPicker": [],
    "actionDirection"             : "Введите цифрами без пробелов и иных знаков",
    "arrURLImageForTask": []
}